apfid/__init__.py
tests/test_af_ids.py
tests/test_apfid.py
apfid-0.2.0.dist-info/LICENSE
apfid-0.2.0.dist-info/METADATA
apfid-0.2.0.dist-info/WHEEL
apfid-0.2.0.dist-info/top_level.txt
apfid-0.2.0.dist-info/RECORD
