Metadata-Version: 2.1
Name: apfid
Version: 0.2.0
Summary: APFID - Arbitrary Protein Fragment IDentifier parser
Author-email: Laboratory of structural proteomics in the IBMC <kirill.s.nikolsky@yandex.ru>
Project-URL: Homepage, https://github.com/protdb/apfid
Keywords: protein,structure,bioinformatics,fragment,identifier,pdb,alphafold
Classifier: Programming Language :: Python :: 3
Classifier: Programming Language :: Python :: 3.10
Classifier: Programming Language :: Python :: 3.11
Classifier: License :: OSI Approved :: MIT License
Classifier: Operating System :: OS Independent
Classifier: Topic :: Scientific/Engineering :: Bio-Informatics
Classifier: Topic :: Software Development :: Libraries :: Python Modules
Requires-Python: >=3.10
License-File: LICENSE
